{
  "welcome_message": {
    "attachment": {
      "type": "template",
      "payload": {
        "template_type": "generic",
        "elements": [
          {
            "title": "Peter",
            "subtitle": "#hello#",
            "item_url": "https://www.facebook.com/HiPeterMessageConsumerUSA/",
            "image_url": "https://scontent-cdg2-1.xx.fbcdn.net/v/t1.0-9/13043430_451569165036075_8900228992336310588_n.png?oh=d0f07b4ddd27ac40a9092eb95e10095a&oe=581F4CEB",
            "buttons": [
              {
                "type": "postback",
                "payload": "{\"action\":\"self.start(senderId)\"}",
                "title": "#start#"
              }
            ]
          }
        ]
      }
    }
  },
  "start_message": {
    "attachment": {
      "type": "template",
      "payload": {
        "template_type": "button",
        "text": "#explain#",
        "buttons":[{
          "type":"postback",
          "title":"#start_btn#",
          "payload":"{action:start}"
        }]
      }
    }
  }
}
